{
  "hints": [],
  "groups": [
    {
      "sourceType": "com.paul.entity.User",
      "name": "User",
      "type": "com.paul.entity.User"
    },
    {
      "sourceType": "com.paul.config.DruidConfig",
      "name": "spring.datasource",
      "sourceMethod": "public javax.sql.DataSource druidDataSource() ",
      "type": "javax.sql.DataSource"
    }
  ],
  "properties": [
    {
      "sourceType": "com.paul.entity.User",
      "name": "User.age",
      "type": "java.lang.Integer"
    },
    {
      "sourceType": "com.paul.entity.User",
      "name": "User.name",
      "type": "java.lang.String"
    },
    {
      "sourceType": "com.paul.entity.User",
      "name": "User.number",
      "type": "java.lang.Integer"
    },
    {
      "sourceType": "com.paul.entity.User",
      "name": "User.user-id",
      "type": "java.lang.Integer"
    }
  ]
}